pylontech/__init__.py
pylontech/pylontech_base.py
pylontech/pylontech_decode.py
pylontech/pylontech_encode.py
pylontech/pylontech_stack.py
pylontech-0.1.2.dist-info/LICENSE
pylontech-0.1.2.dist-info/METADATA
pylontech-0.1.2.dist-info/WHEEL
pylontech-0.1.2.dist-info/top_level.txt
pylontech-0.1.2.dist-info/RECORD
