Metadata-Version: 2.1
Name: pylontech
Version: 0.1.2
Summary: Communicate to Pylontech batteries using a RS485 interface
Home-page: https://github.com/Tomcat42/pylontech-python/
Author: Bernd Singer
Author-email: singer@nefkom.net
License: MIT
Project-URL: Bug Tracker, https://github.com/Tomcat42/pylontech-python/issues
Keywords: pylontech pylon RS485 lithium battery US2000 US2000C US3000
Classifier: Development Status :: 4 - Beta
Classifier: Topic :: Utilities
Classifier: Intended Audience :: Developers
Classifier: License :: OSI Approved :: MIT License
Classifier: Programming Language :: Python :: 3
Classifier: Programming Language :: Python :: 3.6
Classifier: Programming Language :: Python :: 3.8
Classifier: Programming Language :: Python :: 3.9
Classifier: Operating System :: OS Independent
Requires-Python: >=3.6
License-File: LICENSE
Requires-Dist: pyserial
